{
    "commands": {
        "ignoredchannels": {
            "channel_already_ignored": "%channel% já está sendo ignorado",
            "channel_now_ignored": "%channel% será ignorado por ganhar experiência",
            "channel_not_ignored": "%channel% não está sendo ignorado",
            "channel_now_not_ignored": "%channel% não será ignorado por ganhar experiência",
            "channel_list_title": "Canais ignorados"
        },
        "ignoredroles": {
            "role_already_ignored": "%role% já está sendo ignorado",
            "role_now_ignored": "%role% será ignorado por ganhar experiência",
            "role_not_ignored": "%role% não está sendo ignorado",
            "role_now_not_ignored": "%role% não será ignorado por ganhar experiência",
            "role_list_title": "Cargos Ignorados"
        },
        "leaderboard": {
            "leaderboard_title": "Melhores membros %page_size% (Página %page%/%total_pages%)"
        },
        "level": {
            "not_spoken_yet": "Você não falou onde o bot pode vê-lo ainda",
            "your_current_level": "Seu nível atual é **%level%**\nVocê precisa de **%xp%** xp para chegar ao próximo nível",
            "user_not_spoken_yet": "%user% nunca falou antes",
            "user_current_level": "O nível atual de %user%é **%level%**\nO usuário precisa de **%xp%** xp para chegar ao próximo nível"
        },
        "levelroles": {
            "role_already_used": "%role% já está sendo usado para um nível",
            "level_must_be_positive": "O nível deve ser um número positivo",
            "role_granted": "%role% será concedido no **nível %level%**",
            "role_granted_status": "%role% será concedido no **Nível %level%**\n**Status**:\nAtualmente adicionando este cargo a %amount% membros",
            "role_granted_status_complete": "%role% será concedido no **Nível %level%**\n**Estado**:\nCargo adicionado a %amount% membros",
            "role_not_used": "%role% não está sendo usado para um nível",
            "role_removed": "%role% não será mais concedido no **Nível %level%**"
        },
        "levels": {
            "user_doesnt_exist": "%user% não conversou no chat desde que o bot foi adicionado",
            "level_to_give_must_be_positive": "Os níveis a serem fornecidos devem ser um número positivo",
            "levels_added": "Dado %amount% nível%plural% a %user%",
            "level_to_take_must_be_positive": "Os níveis a serem tomados devem ser um número positivo",
            "levels_taken": "Tirado %amount% nível%plural% de %user%"
        },
        "settings": {
            "notification_channel_updated": "Atualizado com sucesso as notificações do nível acima para serem enviadas em %channel%",
            "notification_type_reply_label": "Responder à mensagem",
            "notification_type_reply_description": "Enviar a mensagem de nível acima respondendo à mensagem que acionou o nível superior",
            "notification_type_channel_label": "Especificar o canal",
            "notification_type_channel_description": "Enviar a mensagem de nível em um canal definido",
            "notification_type_dm_label": "Mensagens Diretas",
            "notification_type_dm_description": "Enviar a mensagem de nível acima através de mensagens diretas",
            "notification_type_disabled_label": "Desabilitado",
            "notification_type_disabled_description": "Desativar mensagens de nível acima",
            "please_select": "Por favor, selecione o tipo de notificações que deseja abaixo...",
            "role_type_stacked": "Os usuários agora terão funções empilhadas e seus papéis anteriores não serão removidos",
            "role_type_single": "Os usuários agora terão papéis únicos e seus papéis anteriores serão removidos",
            "multiplier_set": "Esta guilda agora tem um multiplicador **%multiplier%x ** atribuído"
        },
        "xp": {
            "user_doesnt_exist": "%user% não conversou no chat desde que o bot foi adicionado",
            "xp_to_give_must_be_positive": "Xp para dar deve ser um número positivo",
            "xp_added": "Dados %amount% xp para %user%",
            "xp_to_take_must_be_positive": "Xp a ser tomada deve ser um número positivo",
            "xp_taken": "Tirada %amount% xp de %user%"
        }
    },
    "events": {
        "message_create": {
            "message_level_up_reply": "Parabéns %user%! Você se classificou no nível %level%",
            "message_level_up_channel": "Parabéns %user%! Você se classificou até o nível %level%",
            "message_level_up_dm": "Parabéns %user%! Você se classificou até o nível %level%"
        }
    },
    "menus": {
        "guild_settings_notifications": {
            "reply": "As notificações do nível acima foram atualizadas com sucesso para serem enviadas via **respostas**",
            "channel": "Por favor, use o comando de barra `/settings notifications` e especifique o Canal",
            "dm": "As notificações de nível acima foram atualizadas com sucesso para serem enviadas via **Mensagens Diretas**",
            "disable": "Atualizado com sucesso as notificações de nível acima para serem desativadas"
        }
    },
    "generic": {
        "error": "Houve um erro ao executar esta interação.\nPor favor, forneça o código de erro **%error_code%** para a equipe de suporte",
        "access_denied": "Acesso negado"
    }
}
